gdrive_link_maker/__init__.py
gdrive_link_maker-1.0.0.dist-info/METADATA
gdrive_link_maker-1.0.0.dist-info/WHEEL
gdrive_link_maker-1.0.0.dist-info/top_level.txt
gdrive_link_maker-1.0.0.dist-info/RECORD
